odoo8_addon_base_delivery_carrier_label-8.0.1.2.0.99.dev52-py3.8-nspkg.pth
odoo_addons/base_delivery_carrier_label/README.rst
odoo_addons/base_delivery_carrier_label/__init__.py
odoo_addons/base_delivery_carrier_label/__openerp__.py
odoo_addons/base_delivery_carrier_label/carrier_account.py
odoo_addons/base_delivery_carrier_label/delivery.py
odoo_addons/base_delivery_carrier_label/delivery_view.xml
odoo_addons/base_delivery_carrier_label/res_config_view.xml
odoo_addons/base_delivery_carrier_label/stock.py
odoo_addons/base_delivery_carrier_label/stock_view.xml
odoo_addons/base_delivery_carrier_label/i18n/am.po
odoo_addons/base_delivery_carrier_label/i18n/ar.po
odoo_addons/base_delivery_carrier_label/i18n/base_delivery_carrier_label.pot
odoo_addons/base_delivery_carrier_label/i18n/bg.po
odoo_addons/base_delivery_carrier_label/i18n/bs.po
odoo_addons/base_delivery_carrier_label/i18n/ca.po
odoo_addons/base_delivery_carrier_label/i18n/ca_ES.po
odoo_addons/base_delivery_carrier_label/i18n/cs.po
odoo_addons/base_delivery_carrier_label/i18n/da.po
odoo_addons/base_delivery_carrier_label/i18n/de.po
odoo_addons/base_delivery_carrier_label/i18n/el_GR.po
odoo_addons/base_delivery_carrier_label/i18n/en_GB.po
odoo_addons/base_delivery_carrier_label/i18n/es.po
odoo_addons/base_delivery_carrier_label/i18n/es_AR.po
odoo_addons/base_delivery_carrier_label/i18n/es_CL.po
odoo_addons/base_delivery_carrier_label/i18n/es_CO.po
odoo_addons/base_delivery_carrier_label/i18n/es_CR.po
odoo_addons/base_delivery_carrier_label/i18n/es_DO.po
odoo_addons/base_delivery_carrier_label/i18n/es_EC.po
odoo_addons/base_delivery_carrier_label/i18n/es_MX.po
odoo_addons/base_delivery_carrier_label/i18n/es_PE.po
odoo_addons/base_delivery_carrier_label/i18n/es_PY.po
odoo_addons/base_delivery_carrier_label/i18n/es_VE.po
odoo_addons/base_delivery_carrier_label/i18n/et.po
odoo_addons/base_delivery_carrier_label/i18n/eu.po
odoo_addons/base_delivery_carrier_label/i18n/fa.po
odoo8_addon_base_delivery_carrier_label-8.0.1.2.0.99.dev52.dist-info/METADATA
odoo8_addon_base_delivery_carrier_label-8.0.1.2.0.99.dev52.dist-info/WHEEL
odoo8_addon_base_delivery_carrier_label-8.0.1.2.0.99.dev52.dist-info/namespace_packages.txt
odoo8_addon_base_delivery_carrier_label-8.0.1.2.0.99.dev52.dist-info/top_level.txt
odoo8_addon_base_delivery_carrier_label-8.0.1.2.0.99.dev52.dist-info/RECORD
